{
  "_class": "shapePath",
  "booleanOperation": -1,
  "clippingMaskMode": 0,
  "do_objectID": "1F4ECE9E-04D2-44FC-A7D3-4BB3FA1DB45D",
  "edited": true,
  "exportOptions": {
    "_class": "exportOptions",
    "exportFormats": [
    ],
    "includedLayerIds": [
    ],
    "layerOptions": 0,
    "shouldTrim": false
  },
  "frame": {
    "_class": "rect",
    "constrainProportions": false,
    "height": 2.346992489497714,
    "width": 2.474434630607989,
    "x": 11.6616037854047,
    "y": 23.63920980339811
  },
  "hasClippingMask": false,
  "isClosed": false,
  "isFixedToViewport": false,
  "isFlippedHorizontal": false,
  "isFlippedVertical": false,
  "isLocked": false,
  "isVisible": true,
  "layerListExpandedType": 0,
  "name": "Path",
  "nameIsFixed": false,
  "pointRadiusBehaviour": 1,
  "points": [
    {
      "_class": "curvePoint",
      "cornerRadius": 0,
      "curveFrom": "{0.85787867825699049, 0.44955400744877727}",
      "curveMode": 1,
      "curveTo": "{0.85787867825699049, 0.44955400744877727}",
      "hasCurveFrom": false,
      "hasCurveTo": false,
      "point": "{0.85787867825699049, 0.44955400744877727}"
    },
    {
      "_class": "curvePoint",
      "cornerRadius": 0,
      "curveFrom": "{0.06392172703000211, -0.034162075100324318}",
      "curveMode": 4,
      "curveTo": "{0.14201585338020073, 0.013866472103128018}",
      "hasCurveFrom": true,
      "hasCurveTo": false,
      "point": "{0.14201585338020073, 0.013866472103128018}"
    },
    {
      "_class": "curvePoint",
      "cornerRadius": 0,
      "curveFrom": "{-0.0055862990878792007, 0.33085684690818901}",
      "curveMode": 4,
      "curveTo": "{0.00047024937047035649, 0.046457271991187744}",
      "hasCurveFrom": true,
      "hasCurveTo": true,
      "point": "{0.00047024937047035649, 0.19568882937335852}"
    },
    {
      "_class": "curvePoint",
      "cornerRadius": 0,
      "curveFrom": "{0.14364281434580981, 0.55075701762748597}",
      "curveMode": 4,
      "curveTo": "{0.047118983043369568, 0.46156603020032727}",
      "hasCurveFrom": false,
      "hasCurveTo": true,
      "point": "{0.14364281434580981, 0.55075701762748597}"
    },
    {
      "_class": "curvePoint",
      "cornerRadius": 0,
      "curveFrom": "{0.93597280460717058, 1.0344731001765877}",
      "curveMode": 4,
      "curveTo": "{0.85950563922259959, 0.98644455297313527}",
      "hasCurveFrom": true,
      "hasCurveTo": false,
      "point": "{0.85950563922259959, 0.98644455297313527}"
    },
    {
      "_class": "curvePoint",
      "cornerRadius": 0,
      "curveFrom": "{1.0061283511249535, 0.66969081154901522}",
      "curveMode": 4,
      "curveTo": "{0.99942428226670232, 0.95042314257054605}",
      "hasCurveFrom": true,
      "hasCurveTo": true,
      "point": "{0.99942428226670232, 0.80462219570290472}"
    },
    {
      "_class": "curvePoint",
      "cornerRadius": 0,
      "curveFrom": "{0.85787867825699049, 0.44955400744875779}",
      "curveMode": 4,
      "curveTo": "{0.95399857741142091, 0.53892289094800461}",
      "hasCurveFrom": false,
      "hasCurveTo": true,
      "point": "{0.85787867825699049, 0.44955400744875779}"
    }
  ],
  "resizingConstraint": 63,
  "resizingType": 0,
  "rotation": 0,
  "shouldBreakMaskChain": false,
  "style": {
    "_class": "style",
    "blur": {
      "_class": "blur",
      "center": "{0.5, 0.5}",
      "isEnabled": false,
      "motionAngle": 0,
      "radius": 4.025808555999999,
      "saturation": 1,
      "type": 0
    },
    "borderOptions": {
      "_class": "borderOptions",
      "dashPattern": [
      ],
      "isEnabled": true,
      "lineCapStyle": 0,
      "lineJoinStyle": 0
    },
    "borders": [
    ],
    "colorControls": {
      "_class": "colorControls",
      "brightness": 0,
      "contrast": 1,
      "hue": 0,
      "isEnabled": false,
      "saturation": 1
    },
    "contextSettings": {
      "_class": "graphicsContextSettings",
      "blendMode": 0,
      "opacity": 0.2
    },
    "do_objectID": "BD0860E8-5911-4FCD-BA3B-027A734A7565",
    "endMarkerType": 0,
    "fills": [
      {
        "_class": "fill",
        "color": {
          "_class": "color",
          "alpha": 1,
          "blue": 0.9882352941176471,
          "green": 0.9882352941176471,
          "red": 0.9882352941176471
        },
        "contextSettings": {
          "_class": "graphicsContextSettings",
          "blendMode": 0,
          "opacity": 1
        },
        "fillType": 0,
        "gradient": {
          "_class": "gradient",
          "elipseLength": 0,
          "from": "{0.5, 0}",
          "gradientType": 0,
          "stops": [
            {
              "_class": "gradientStop",
              "color": {
                "_class": "color",
                "alpha": 1,
                "blue": 1,
                "green": 1,
                "red": 1
              },
              "position": 0
            },
            {
              "_class": "gradientStop",
              "color": {
                "_class": "color",
                "alpha": 1,
                "blue": 0,
                "green": 0,
                "red": 0
              },
              "position": 1
            }
          ],
          "to": "{0.5, 1}"
        },
        "isEnabled": true,
        "noiseIndex": 0,
        "noiseIntensity": 0,
        "patternFillType": 1,
        "patternTileScale": 1
      }
    ],
    "innerShadows": [
    ],
    "miterLimit": 10,
    "shadows": [
    ],
    "startMarkerType": 0,
    "windingRule": 0
  }
}