{
  "_class": "group",
  "booleanOperation": -1,
  "clippingMaskMode": 0,
  "do_objectID": "C16C37D8-4A09-4E19-97FB-FD2669EAC9EC",
  "exportOptions": {
    "_class": "exportOptions",
    "exportFormats": [
    ],
    "includedLayerIds": [
    ],
    "layerOptions": 0,
    "shouldTrim": false
  },
  "frame": {
    "_class": "rect",
    "constrainProportions": false,
    "height": 260,
    "width": 240,
    "x": 0,
    "y": 0
  },
  "groupLayout": {
    "_class": "MSImmutableFreeformGroupLayout"
  },
  "hasClickThrough": false,
  "hasClippingMask": false,
  "isFixedToViewport": false,
  "isFlippedHorizontal": false,
  "isFlippedVertical": false,
  "isLocked": false,
  "isVisible": true,
  "layerListExpandedType": 0,
  "layers": [
    {
      "class": "rectangle",
      "id": "760B9A2A-4140-43E4-B047-D7C0F8CCE790"
    },
    {
      "class": "rectangle",
      "id": "05690DAA-6510-463B-85A1-793B3A673536"
    }
  ],
  "name": "Rectangle",
  "nameIsFixed": false,
  "resizingConstraint": 63,
  "resizingType": 0,
  "rotation": 0,
  "shouldBreakMaskChain": false,
  "style": {
    "_class": "style",
    "blur": {
      "_class": "blur",
      "center": "{0.5, 0.5}",
      "isEnabled": false,
      "motionAngle": 0,
      "radius": 10,
      "saturation": 1,
      "type": 0
    },
    "borderOptions": {
      "_class": "borderOptions",
      "dashPattern": [
      ],
      "isEnabled": true,
      "lineCapStyle": 0,
      "lineJoinStyle": 0
    },
    "borders": [
    ],
    "colorControls": {
      "_class": "colorControls",
      "brightness": 0,
      "contrast": 1,
      "hue": 0,
      "isEnabled": false,
      "saturation": 1
    },
    "contextSettings": {
      "_class": "graphicsContextSettings",
      "blendMode": 0,
      "opacity": 1
    },
    "do_objectID": "5167F1B1-BABA-49E9-B8F1-C80703D448A5",
    "endMarkerType": 0,
    "fills": [
    ],
    "innerShadows": [
    ],
    "miterLimit": 10,
    "shadows": [
    ],
    "startMarkerType": 0,
    "windingRule": 1
  }
}