{
  "_class": "group",
  "booleanOperation": -1,
  "clippingMaskMode": 0,
  "do_objectID": "E41826CF-F4A6-4DB0-8C3C-DDEADB4D3830",
  "exportOptions": {
    "_class": "exportOptions",
    "exportFormats": [
    ],
    "includedLayerIds": [
    ],
    "layerOptions": 0,
    "shouldTrim": false
  },
  "frame": {
    "_class": "rect",
    "constrainProportions": false,
    "height": 243,
    "width": 1440,
    "x": 0,
    "y": 662
  },
  "groupLayout": {
    "_class": "MSImmutableFreeformGroupLayout"
  },
  "hasClickThrough": false,
  "hasClippingMask": false,
  "isFixedToViewport": false,
  "isFlippedHorizontal": false,
  "isFlippedVertical": false,
  "isLocked": false,
  "isVisible": true,
  "layerListExpandedType": 0,
  "layers": [
    {
      "class": "group",
      "id": "10AFED1F-E56D-418F-BF32-218C284920F4"
    },
    {
      "class": "group",
      "id": "A8D1227D-654A-496C-9024-3028B84CBDD5"
    },
    {
      "class": "text",
      "id": "8E7E5DF2-047C-4009-AAA4-E9C436DE4E59"
    },
    {
      "class": "text",
      "id": "F78C1363-5BEC-42D6-939D-0763D4F4190C"
    },
    {
      "class": "group",
      "id": "65C85E46-A541-4DC4-8CA8-D2C499EE7AB0"
    },
    {
      "class": "group",
      "id": "3403F283-9710-44EB-9C90-9801544838AF"
    }
  ],
  "name": "Advert",
  "nameIsFixed": true,
  "resizingConstraint": 63,
  "resizingType": 0,
  "rotation": 0,
  "shouldBreakMaskChain": false,
  "style": {
    "_class": "style",
    "blur": {
      "_class": "blur",
      "center": "{0.5, 0.5}",
      "isEnabled": false,
      "motionAngle": 0,
      "radius": 10,
      "saturation": 1,
      "type": 0
    },
    "borderOptions": {
      "_class": "borderOptions",
      "dashPattern": [
      ],
      "isEnabled": true,
      "lineCapStyle": 0,
      "lineJoinStyle": 0
    },
    "borders": [
    ],
    "colorControls": {
      "_class": "colorControls",
      "brightness": 0,
      "contrast": 1,
      "hue": 0,
      "isEnabled": false,
      "saturation": 1
    },
    "contextSettings": {
      "_class": "graphicsContextSettings",
      "blendMode": 0,
      "opacity": 1
    },
    "do_objectID": "A1101AE0-F6E0-4E4F-B547-79BA75B34BDF",
    "endMarkerType": 0,
    "fills": [
    ],
    "innerShadows": [
    ],
    "miterLimit": 10,
    "shadows": [
    ],
    "startMarkerType": 0,
    "windingRule": 1
  }
}